README.md
setup.py
testflows.egg-info/PKG-INFO
testflows.egg-info/SOURCES.txt
testflows.egg-info/dependency_links.txt
testflows.egg-info/not-zip-safe
testflows.egg-info/requires.txt
testflows.egg-info/top_level.txt
testflows/version/__init__.py