Metadata-Version: 2.1
Name: testflows
Version: 2.4.19
Summary: TestFlows.com Open-Source Software Testing Framework
Home-page: https://github.com/testflows/testflows
Author: Vitaliy Zakaznikov
Author-email: vzakaznikov@testflows.com
License: Apache-2.0
Classifier: Programming Language :: Python :: 3
Classifier: License :: OSI Approved :: Apache Software License
Classifier: Operating System :: POSIX :: Linux
Requires-Python: >=3.8
Requires-Dist: testflows.core==2.0.250110.1002922
Requires-Dist: testflows.asserts==7.1.240701.1195420
Requires-Dist: testflows.snapshots==1.0.241118.1155431
Requires-Dist: testflows.stash==1.1.230317.1211113
Requires-Dist: testflows.uexpect==1.7.230414.1210501
Requires-Dist: testflows.connect==1.7.240918.1165507
Requires-Dist: testflows.database==1.6.200713.1142213
Provides-Extra: dev
